AUTHORS
ChangeLog
HISTORY.rst
LICENSE
README.rst
requirements.txt
setup.cfg
setup.py
debian/rules
docs/Makefile
docs/make.bat
docs/source/conf.py
docs/source/index.rst
docs/source/main/actions.rst
docs/source/main/api.rst
docs/source/main/columns.rst
docs/source/main/filters.rst
docs/source/main/forms.rst
docs/source/main/generic.rst
docs/source/main/panel.rst
docs/source/main/reactjs.rst
docs/source/main/tables.rst
docs/source/main/tutorial.rst
horizon_contrib/__init__.py
horizon_contrib/dashboard.py
horizon_contrib/models.py
horizon_contrib/panel.py
horizon_contrib/urls.py
horizon_contrib.egg-info/PKG-INFO
horizon_contrib.egg-info/SOURCES.txt
horizon_contrib.egg-info/dependency_links.txt
horizon_contrib.egg-info/not-zip-safe
horizon_contrib.egg-info/pbr.json
horizon_contrib.egg-info/requires.txt
horizon_contrib.egg-info/top_level.txt
horizon_contrib/api/__init__.py
horizon_contrib/api/base.py
horizon_contrib/api/managers.py
horizon_contrib/api/models.py
horizon_contrib/api/pagination.py
horizon_contrib/api/response.py
horizon_contrib/common/__init__.py
horizon_contrib/common/content_type.py
horizon_contrib/common/model_registry.py
horizon_contrib/compat/__init__.py
horizon_contrib/compat/decorators.py
horizon_contrib/forms/__init__.py
horizon_contrib/forms/forms.py
horizon_contrib/forms/models.py
horizon_contrib/forms/panel.py
horizon_contrib/forms/urls.py
horizon_contrib/forms/utils.py
horizon_contrib/forms/views.py
horizon_contrib/generic/__init__.py
horizon_contrib/generic/panel.py
horizon_contrib/generic/tables.py
horizon_contrib/generic/urls.py
horizon_contrib/generic/views.py
horizon_contrib/locale/cs/LC_MESSAGES/django.po
horizon_contrib/static/contrib/css/cubism.css
horizon_contrib/static/contrib/js/cubism.js
horizon_contrib/static/contrib/js/graph_utils.js
horizon_contrib/tables/__init__.py
horizon_contrib/tables/actions.py
horizon_contrib/tables/base.py
horizon_contrib/tables/filters.py
horizon_contrib/tables/views.py
horizon_contrib/tables/columns/__init__.py
horizon_contrib/tables/columns/graph.py
horizon_contrib/tables/columns/list.py
horizon_contrib/templates/horizon_contrib/forms/_create.html
horizon_contrib/templates/horizon_contrib/forms/create.html
